botoy/__init__.py
botoy/__main__.py
botoy/__version__.py
botoy/_internal/__init__.py
botoy/_internal/action.py
botoy/_internal/cli.py
botoy/_internal/client.py
botoy/_internal/context.py
botoy/_internal/contrib.py
botoy/_internal/keys.py
botoy/_internal/log.py
botoy/_internal/mahiro.py
botoy/_internal/pool.py
botoy/_internal/receiver.py
botoy/_internal/runner.py
botoy/_internal/schedule.py
botoy/_internal/sugar.py
botoy/_internal/utils.py
botoy/_internal/config/__init__.py
botoy/_internal/config/config.py
botoy/_internal/config/constants.py
botoy/_internal/config/util.py
botoy/_internal/models/__init__.py
botoy/_internal/models/friend_msg.py
botoy/_internal/models/group_msg.py
botoy-9.11.dist-info/LICENSE
botoy-9.11.dist-info/METADATA
botoy-9.11.dist-info/WHEEL
botoy-9.11.dist-info/entry_points.txt
botoy-9.11.dist-info/top_level.txt
botoy-9.11.dist-info/RECORD
