Metadata-Version: 2.1
Name: botoy
Version: 9.11
Summary: OPQBot/IOTQQ/IOTBot的Python开发助手
Home-page: https://github.com/xiyaowong/botoy
Author: wongxy
Author-email: xiyao.wong@foxmail.com
License: MIT
Keywords: iotbot,iotqq,OPQ,OPQBot,botoy
Platform: UNKNOWN
Requires-Python: >=3.8
Requires-Dist: httpx
Requires-Dist: websockets
Requires-Dist: loguru
Requires-Dist: click
Requires-Dist: prettytable
Requires-Dist: apscheduler
Requires-Dist: pydantic <2.0
Requires-Dist: colorama
Requires-Dist: fastapi
Requires-Dist: uvicorn
